gke_log_tools/__init__.py
gke_log_tools/gcp_tools.py
gke_log_tools/gcs_signing_credentials.py
gke_log_tools/pyarmor_runtime_000000/__init__.py
gke_log_tools-1.0.6.dist-info/licenses/LICENSE
gke_log_tools-1.0.6.dist-info/METADATA
gke_log_tools-1.0.6.dist-info/WHEEL
gke_log_tools-1.0.6.dist-info/top_level.txt
gke_log_tools-1.0.6.dist-info/RECORD
