Metadata-Version: 2.4
Name: gke-log-tools
Version: 1.0.6
Summary: [Protected] GKE Log Management Tools with GCS Archive Access
License: MIT
Project-URL: Homepage, https://github.com/yourusername/gke-log-tools
Project-URL: Repository, https://github.com/yourusername/gke-log-tools
Keywords: gke,logs,gcs,archive,nfs
Classifier: Development Status :: 4 - Beta
Classifier: Intended Audience :: Developers
Classifier: License :: OSI Approved :: MIT License
Classifier: Programming Language :: Python :: 3
Classifier: Programming Language :: Python :: 3.8
Classifier: Programming Language :: Python :: 3.9
Classifier: Programming Language :: Python :: 3.10
Classifier: Programming Language :: Python :: 3.11
Requires-Python: >=3.8
License-File: LICENSE
Requires-Dist: google-cloud-storage>=2.10.0
Requires-Dist: google-auth>=2.23.0
Requires-Dist: gke-cache-builder>=1.0.6
Dynamic: license-file
